LICENSE
MANIFEST.in
README
bootstrap.py
buildout.cfg
mkblog
requirements.txt
setup.py
bigmouth_example/__init__.py
bigmouth_example/development.py
bigmouth_example/production.py
bigmouth_example/settings.py
bigmouth_example/urls.py
bigmouth_example/views.py
bigmouth_example/blog_content/alt/100512-unfortunate.rst
bigmouth_example/blog_content/alt/110613-man-from-nantucket.rst
bigmouth_example/blog_content/code/100713-unix_exit_status_code_reference.rst
bigmouth_example/blog_content/code/110421-finally-static.rst
bigmouth_example/blog_content/code/110730-i-use-this.rst
bigmouth_example/blog_content/code/111126-heroku-cedar-static.rst
bigmouth_example/blog_content/pages/about.rst
bigmouth_example/blog_content/pages/resume.rst
bigmouth_example/etc/postgres/create_db_and_user
bigmouth_example/etc/postgres/db.txt
bigmouth_example/etc/postgres/pgreset
bigmouth_example/static/css/main.css
bigmouth_example/static/css/pygment.css
bigmouth_example/static/css/reset.css
bigmouth_example/static/css/wide.css
bigmouth_example/static/images/icons/delicious.png
bigmouth_example/static/images/icons/lastfm.png
bigmouth_example/static/images/icons/linkedin.png
bigmouth_example/static/images/icons/rss.png
bigmouth_example/static/images/icons/twitter.png
bigmouth_example/templates/404.html
bigmouth_example/templates/500.html
bigmouth_example/templates/bigmouth/archives.html
bigmouth_example/templates/bigmouth/article.html
bigmouth_example/templates/bigmouth/author.html
bigmouth_example/templates/bigmouth/authors.html
bigmouth_example/templates/bigmouth/base.html
bigmouth_example/templates/bigmouth/categories.html
bigmouth_example/templates/bigmouth/category.html
bigmouth_example/templates/bigmouth/comments.html
bigmouth_example/templates/bigmouth/index.html
bigmouth_example/templates/bigmouth/page.html
bigmouth_example/templates/bigmouth/pagination.html
bigmouth_example/templates/bigmouth/tag.html
bigmouth_example/templates/bigmouth/tags.html
src/bigmouth.egg-info/PKG-INFO
src/bigmouth.egg-info/SOURCES.txt
src/bigmouth.egg-info/dependency_links.txt
src/bigmouth.egg-info/requires.txt
src/bigmouth.egg-info/top_level.txt
