Metadata-Version: 1.0
Name: bigmouth
Version: 0.1.3
Summary: Django interface to the Pelican static blog generator.
Home-page: https://github.com/devopsni/django-bigmouth
Author: Djerd Flanagan
Author-email: gflanagan@devopsni.com
License: BSD
Download-URL: http://pypi.python.org/packages/source/b/bigmouth/bigmouth-0.1.3.tar.gz
Platform: UNKNOWN
Classifier: Development Status :: 1 - Planning
Classifier: Intended Audience :: Developers
Classifier: License :: OSI Approved :: BSD License
Classifier: Programming Language :: Python
Classifier: Topic :: Software Development :: Libraries
Classifier: Topic :: Software Development :: Libraries :: Python Modules
